MANIFEST.in
ophanim.py
setup.py
ophanim.egg-info/PKG-INFO
ophanim.egg-info/SOURCES.txt
ophanim.egg-info/dependency_links.txt
ophanim.egg-info/entry_points.txt
ophanim.egg-info/requires.txt
ophanim.egg-info/top_level.txt