Metadata-Version: 1.0
Name: ophanim
Version: 2017.4.18.1739
Summary: monitoring and notifications for measurements such as Bitcoin value and internet connection security
Home-page: https://github.com/wdbm/ophanim
Author: Will Breaden Madden
Author-email: wbm@protonmail.ch
License: GPLv3
Platform: UNKNOWN
